LICENSE
MANIFEST.in
README.md
setup.py
pythondata_software_picolibc/__init__.py
pythondata_software_picolibc.egg-info/PKG-INFO
pythondata_software_picolibc.egg-info/SOURCES.txt
pythondata_software_picolibc.egg-info/dependency_links.txt
pythondata_software_picolibc.egg-info/not-zip-safe
pythondata_software_picolibc.egg-info/top_level.txt
pythondata_software_picolibc/data/.clang-format
pythondata_software_picolibc/data/.editorconfig
pythondata_software_picolibc/data/.git
pythondata_software_picolibc/data/.gitattributes
pythondata_software_picolibc/data/.gitignore
pythondata_software_picolibc/data/CMakeLists.txt
pythondata_software_picolibc/data/CODE_OF_CONDUCT.md
pythondata_software_picolibc/data/CONTRIBUTING.md
pythondata_software_picolibc/data/COPYING.GPL2
pythondata_software_picolibc/data/COPYING.NEWLIB
pythondata_software_picolibc/data/COPYING.picolibc
pythondata_software_picolibc/data/README.md
pythondata_software_picolibc/data/cross.tmpl
pythondata_software_picolibc/data/find-copyright
pythondata_software_picolibc/data/make-copyrights
pythondata_software_picolibc/data/meson.build
pythondata_software_picolibc/data/meson_options.txt
pythondata_software_picolibc/data/picolibc.h.in
pythondata_software_picolibc/data/picolibc.ld.in
pythondata_software_picolibc/data/picolibc.specs.in
pythondata_software_picolibc/data/test.specs.in
pythondata_software_picolibc/data/.github/CODEOWNERS
pythondata_software_picolibc/data/.github/Dockerfile
pythondata_software_picolibc/data/.github/do-build
pythondata_software_picolibc/data/.github/do-cmake-test
pythondata_software_picolibc/data/.github/do-many
pythondata_software_picolibc/data/.github/do-test
pythondata_software_picolibc/data/.github/packages.txt
pythondata_software_picolibc/data/.github/workflows/head
pythondata_software_picolibc/data/.github/workflows/linux.yml
pythondata_software_picolibc/data/.github/workflows/macos.yml
pythondata_software_picolibc/data/.github/workflows/make-workflow
pythondata_software_picolibc/data/.github/workflows/steps-cmake
pythondata_software_picolibc/data/.github/workflows/steps-fortify-source
pythondata_software_picolibc/data/.github/workflows/steps-head
pythondata_software_picolibc/data/.github/workflows/steps-minsize
