Metadata-Version: 2.1
Name: pythondata-software-picolibc
Version: 1.7.6.post184
Summary: Python module containing data files for picolibc - a C library designed for embedded 32- and 64- bit systems. software.
Home-page: https://github.com/litex-hub/pythondata-software-picolibc
Author: LiteX Authors
Author-email: litex@googlegroups.com
Project-URL: Bug Tracker, https://github.com/litex-hub/pythondata-software-picolibc/issues
Project-URL: Source Code, https://github.com/litex-hub/pythondata-software-picolibc
Classifier: Programming Language :: Python :: 3
Classifier: License :: OSI Approved :: BSD License
Classifier: Operating System :: OS Independent
Requires-Python: >=3.5
License-File: LICENSE
